typs/__init__.py
typs/_modidx.py
typs/_tmp.py
typs/core/__init__.py
typs/core/base.py
typs/core/meta.py
typs/core/ptyp.py
typs/core/rchk.py
typs/core/solo.py
typs/inst/__init__.py
typs/inst/duck.py
typs/inst/prot.py
typs/prep/__init__.py
typs/prep/matr.py
typs/prep/mods.py
typs/prep/spec.py
typs/prep/trys.py
typs/util/__init__.py
typs/util/attr.py
typs/util/cons.py
typs/util/enum.py
typs/util/errs.py
typs/util/grds.py
typs/util/imps.py
typs/util/misc.py
typs/util/prop.py
typs/util/prot.py
typs/util/type.py
typs/util/uscr.py
typs-0.0.6.dist-info/LICENSE
typs-0.0.6.dist-info/METADATA
typs-0.0.6.dist-info/WHEEL
typs-0.0.6.dist-info/entry_points.txt
typs-0.0.6.dist-info/top_level.txt
typs-0.0.6.dist-info/RECORD
